[
  {
    "id": "1",
    "category": "tech",
    "title": "Games with loot boxes to get minimum 16 age rating across Europe",
    "source": "BBC News",
    "timeAgo": "Today",
    "imageUrl": "https://images.unsplash.com/photo-1585829365295-ab7cd400c167?auto=format&fit=crop&q=80&w=1000",
    "readTime": "1 min",
    "vibe": "info",
    "summary": [
      "ヨーロッパにおいて、ルートボックス（ゲーム内アイテムがランダムに出てくる仕組み）を含むゲームに、最低16歳以上の年齢制限が導入されます。",
      "この新しい年齢制限は、汎欧州ゲーム情報年齢評価機関（PEGI）によって決定されました。",
      "変更は今年の6月から適用が開始されます。"
    ],
    "whyYouShouldCare": "この動きは、日本のゲーム業界や保護者、ゲーマーが将来的なゲーム規制の動向を考える上で重要な示唆を与える可能性があります。",
    "isComplex": true,
    "eli5Summary": [
      "ゲームの中には、何が出てくるか分からない『くじ引き』みたいな箱があるよね。",
      "ヨーロッパでは、そういうくじ引きがあるゲームは、16歳より小さい子は遊べなくなるんだ。",
      "これは今年の6月から始まるよ。"
    ]
  },
  {
    "id": "2",
    "category": "tech",
    "title": "AI toys for children misread emotions and respond inappropriately, researchers warn",
    "source": "BBC News",
    "timeAgo": "Today",
    "imageUrl": "https://images.unsplash.com/photo-1585829365295-ab7cd400c167?auto=format&fit=crop&q=80&w=1000",
    "readTime": "1 min",
    "vibe": "alert",
    "summary": [
      "ケンブリッジ大学の研究により、AI搭載の子ども向け玩具が感情を誤認識する可能性が指摘されました。",
      "この研究は、AI玩具が子どもの感情を読み違え、不適切な反応をする恐れがあることを警告しています。",
      "AI玩具の感情認識に関する初の本格的な調査結果として注目されています。"
    ],
    "whyYouShouldCare": "AI玩具の普及が進む中、子どもの感情認識の精度や安全性について、保護者や教育関係者が考慮すべき重要な情報です。",
    "isComplex": true,
    "eli5Summary": [
      "AI（人工知能）が入ったおもちゃが、子どもの「楽しい」や「悲しい」といった気持ちを間違えてしまうことがあるんだって。",
      "だから、子どもが悲しいのに、おもちゃが「やったー！」と喜んだり、変な反応をしてしまうかもしれないんだ。",
      "科学者たちが、そんなおもちゃは気をつけようね、と教えてくれているよ。"
    ]
  },
  {
    "id": "3",
    "category": "tech",
    "title": "Grammarly pulls AI author-impersonation tool after backlash",
    "source": "BBC News",
    "timeAgo": "Today",
    "imageUrl": "https://images.unsplash.com/photo-1585829365295-ab7cd400c167?auto=format&fit=crop&q=80&w=1000",
    "readTime": "1 min",
    "vibe": "info",
    "summary": [
      "文章校正ツールGrammarlyが、AIによる「著者なりすまし」機能を批判を受け撤回しました。",
      "この機能は、作家の同意なしに彼らの名前や文体を「AIペルソナ」として利用するものでした。",
      "作家コミュニティから強い反発があり、倫理的な懸念が指摘されたことが撤回の主な理由です。"
    ],
    "whyYouShouldCare": "AIが個人のスタイルや著作物を無断で利用する可能性は、クリエイターだけでなく、将来的にAIサービスを利用する全てのユーザーにとって、倫理と同意の重要性を再認識させるものです。",
    "isComplex": true,
    "eli5Summary": [
      "文章を直してくれるGrammarlyというアプリが、人の書き方を真似するAIの道具を引っ込めました。",
      "それは、作家さんの名前や書き方を、許可なくAIが勝手に使うものだったので、みんなが怒ったからです。",
      "人のものを勝手に使ってはいけない、という大切なルールを守るためのお話です。"
    ]
  },
  {
    "id": "4",
    "category": "business",
    "title": "'We're not profiteering on fuel. But my staff still face abuse'",
    "source": "BBC News",
    "timeAgo": "Today",
    "imageUrl": "https://images.unsplash.com/photo-1585829365295-ab7cd400c167?auto=format&fit=crop&q=80&w=1000",
    "readTime": "1 min",
    "vibe": "negative",
    "summary": [
      "独立系小売業者は、燃料価格の高騰が顧客だけでなく自身にとっても「恐ろしい」状況だと訴えています。",
      "同社は燃料価格の便乗値上げは行っていないと明言しています。",
      "しかし、燃料価格への不満から、現場のスタッフが顧客からの罵倒に晒されている現状を明らかにしました。"
    ],
    "whyYouShouldCare": "燃料価格の高騰は私たちの家計だけでなく、小売店の経営やそこで働く人々の労働環境にも深刻な影響を与えていることを示唆しています。",
    "isComplex": false
  },
  {
    "id": "5",
    "category": "business",
    "title": "Judge says 'no evidence' to justify Federal Reserve probe",
    "source": "BBC News",
    "timeAgo": "Today",
    "imageUrl": "https://images.unsplash.com/photo-1585829365295-ab7cd400c167?auto=format&fit=crop&q=80&w=1000",
    "readTime": "1 min",
    "vibe": "info",
    "summary": [
      "裁判官は、連邦準備制度に対する調査を正当化する「証拠がない」との判断を下しました。",
      "この判決により、中央銀行に対して発行されていた召喚状は阻止されることになります。",
      "Jeanine Pirro氏は、この判決を不服として控訴する意向を表明しています。"
    ],
    "whyYouShouldCare": "アメリカの中央銀行である連邦準備制度の透明性や独立性に関する議論は、世界の金融市場の安定に影響を与え、ひいては日本の経済や金利にも間接的な影響を及ぼす可能性があります。",
    "isComplex": true,
    "eli5Summary": [
      "アメリカのお金を管理する大事な銀行（連邦準備制度）を、ある人が「ちゃんと調べて！」と言いました。",
      "でも、裁判所の偉い人が「調べる理由がないよ」と言って、調べさせないことにしました。",
      "調べたかった人は「納得できないから、もう一度お願いする！」と言っているよ。"
    ]
  },
  {
    "id": "6",
    "category": "business",
    "title": "Petrol retailers in row with government over 'rip off' accusations",
    "source": "BBC News",
    "timeAgo": "Today",
    "imageUrl": "https://images.unsplash.com/photo-1585829365295-ab7cd400c167?auto=format&fit=crop&q=80&w=1000",
    "readTime": "1 min",
    "vibe": "negative",
    "summary": [
      "ガソリン小売業者が、燃料価格高騰を巡る政府の「ぼったくり」との非難に対し反発しています。",
      "小売業者側は、政府閣僚が「扇動的な言葉」を使っていると非難しました。",
      "これを受け、小売業者らは政府との会議から一時的に離脱すると警告しました。"
    ],
    "whyYouShouldCare": "この対立は、将来のガソリン価格や政府の燃料政策に影響を及ぼす可能性があり、私たちの家計や物流コストに直結します。",
    "isComplex": true,
    "eli5Summary": [
      "ガソリンを売るお店と政府が、ガソリンの値段についてケンカしているよ。",
      "政府は「ガソリン代が高すぎるのはお店が悪い！」って言ったんだ。",
      "お店は「そんな言い方ひどい！」って怒って、政府の話し合いに出ないって言ったんだよ。"
    ]
  },
  {
    "id": "7",
    "category": "world",
    "title": "All six crew members killed after US refuelling plane crashes in Iraq",
    "source": "BBC News",
    "timeAgo": "Today",
    "imageUrl": "https://images.unsplash.com/photo-1585829365295-ab7cd400c167?auto=format&fit=crop&q=80&w=1000",
    "readTime": "1 min",
    "vibe": "negative",
    "summary": [
      "米軍の給油機がイラク西部で墜落しました。",
      "搭乗していた乗員6名全員が死亡しました。",
      "この事故は米中央軍によって発表されました。"
    ],
    "whyYouShouldCare": "軍用機の事故は国際情勢の不安定さを示す可能性があり、日本の安全保障や外交政策にも間接的に影響を与える可能性があります。",
    "isComplex": false
  },
  {
    "id": "8",
    "category": "world",
    "title": "Xi's anti-corruption drive began 14 years ago. Why are the purges still going?",
    "source": "BBC News",
    "timeAgo": "Today",
    "imageUrl": "https://images.unsplash.com/photo-1585829365295-ab7cd400c167?auto=format&fit=crop&q=80&w=1000",
    "readTime": "1 min",
    "vibe": "negative",
    "summary": [
      "習近平国家主席による反腐敗運動は14年前に開始されましたが、現在も粛清が続いています。",
      "批判者からは、この粛清が絶対的な忠誠を求める冷酷な権力掌握の動きであると指摘されています。",
      "特に、軍に対する完全な支配を確立しようとする意図が背景にあると見られています。"
    ],
    "whyYouShouldCare": "中国の権力構造と軍の動向は、日本の安全保障や経済関係に間接的な影響を及ぼす可能性があるため、その背景を理解することは重要です。",
    "isComplex": true,
    "eli5Summary": [
      "中国の偉い人（習近平さん）は、悪いことをする人を捕まえる「お掃除」をずっと前からやっています。",
      "でも、そのお掃除が今も続いているのは、みんなが自分に絶対逆らわないようにするため、という人もいます。",
      "特に、国の軍隊を自分の言う通りに動かしたい気持ちが強いみたいです。"
    ]
  },
  {
    "id": "9",
    "category": "world",
    "title": "Ukraine and allies fear easing Russian sanctions will prolong war",
    "source": "BBC News",
    "timeAgo": "Today",
    "imageUrl": "https://images.unsplash.com/photo-1585829365295-ab7cd400c167?auto=format&fit=crop&q=80&w=1000",
    "readTime": "1 min",
    "vibe": "negative",
    "summary": [
      "ウクライナとその同盟国は、ロシアへの制裁緩和が戦争を長期化させる可能性を懸念しています。",
      "ウクライナ大統領は、米国の決定が「平和達成に全く役立たない」と明確に表明しました。",
      "国際社会におけるロシアへの圧力維持の重要性が、改めて議論の焦点となっています。"
    ],
    "whyYouShouldCare": "ロシアへの制裁緩和の動きは、世界の経済や日本の物価、国際情勢にも影響を及ぼす可能性があるため、今後の動向に注目が必要です。",
    "isComplex": true,
    "eli5Summary": [
      "ウクライナという国と、その友達の国々は、ロシアという国へのお仕置き（制裁）を緩めると、戦争がもっと長引くかもしれないと心配しています。",
      "ウクライナのリーダーは、「アメリカの決めたことは、早く仲直りする役には立たないよ」と言っています。",
      "みんなでロシアに「お仕置き」を続けることが、早く平和になるために大切だと考えているようです。"
    ]
  },
  {
    "id": "10",
    "category": "science",
    "title": "Artemis II: Nasa targets early April for Moon mission",
    "source": "BBC News",
    "timeAgo": "Today",
    "imageUrl": "https://images.unsplash.com/photo-1585829365295-ab7cd400c167?auto=format&fit=crop&q=80&w=1000",
    "readTime": "1 min",
    "vibe": "positive",
    "summary": [
      "NASAは、月探査ミッション「アルテミスII」の目標打ち上げ時期を4月上旬に設定しました。",
      "これまで打ち上げを遅らせていた技術的な問題が全て解決されたと発表しています。",
      "これにより、ロケットは月への飛行に向けて準備が整った状態です。"
    ],
    "whyYouShouldCare": "このミッションは、人類の月への再挑戦であり、将来の火星探査への重要な一歩となるため、科学技術の進歩や宇宙への夢に関心を持つ日本人にとって注目すべきニュースです。",
    "isComplex": true,
    "eli5Summary": [
      "NASAというところが、月に行くロケットの準備ができたよと教えてくれました。",
      "前は少し壊れていた部分があったけれど、もう全部直ったんだって。",
      "だから、今年の4月になったら、いよいよ月へ出発するかもしれないよ！"
    ]
  },
  {
    "id": "11",
    "category": "science",
    "title": "Prioritising AI data centres could block new homes, builders warn",
    "source": "BBC News",
    "timeAgo": "Today",
    "imageUrl": "https://images.unsplash.com/photo-1585829365295-ab7cd400c167?auto=format&fit=crop&q=80&w=1000",
    "readTime": "1 min",
    "vibe": "alert",
    "summary": [
      "政府はAIデータセンターの開発を加速するため、電力網への優先アクセスを計画しています。",
      "しかし、建設業界は、この優先措置が新規住宅の建設を妨げる可能性があると警告しています。",
      "AIインフラ整備のための電力供給の優先順位付けが、住宅供給問題に影響を与える懸念が浮上しています。"
    ],
    "whyYouShouldCare": "AIデータセンターへの電力優先供給は、住宅建設の遅延につながり、将来の住まい探しや生活環境に影響を及ぼす可能性があります。",
    "isComplex": true,
    "eli5Summary": [
      "政府は、AIという新しいコンピューターを動かすための大きな建物（データセンター）を早く作りたいと思っています。",
      "そのため、データセンターに電気を一番に送るようにしようと考えています。",
      "でも、そうすると、みんなが住む家を作るための電気が足りなくなり、新しい家が建ちにくくなるかもしれないと、家を作る人たちが心配しています。"
    ]
  },
  {
    "id": "12",
    "category": "science",
    "title": "Secret of hedgehog hearing discovered at far beyond human range",
    "source": "BBC News",
    "timeAgo": "Today",
    "imageUrl": "https://images.unsplash.com/photo-1585829365295-ab7cd400c167?auto=format&fit=crop&q=80&w=1000",
    "readTime": "1 min",
    "vibe": "curious",
    "summary": [
      "研究により、ハリネズミの聴覚の秘密が解明されました。",
      "彼らは人間には聞こえない、非常に高い周波数の音を聞き取れることが判明。",
      "研究チームは音源を再生し、ハリネズミが反応する音の周波数を特定しました。"
    ],
    "whyYouShouldCare": "動物の驚くべき能力を知ることで、生物多様性への理解を深め、新たな技術開発のヒントにもなり得ます。",
    "isComplex": true,
    "eli5Summary": [
      "ハリネズミは、私たち人間には聞こえない、とっても高い音を聞くことができるんだって！",
      "科学者のお兄さんやお姉さんが、ハリネズミに色々な音を聞かせて、どんな音が聞こえるか調べたんだ。",
      "これで、ハリネズミがどうやって周りの世界を感じているのか、もっとよくわかるようになったよ。"
    ]
  },
  {
    "id": "13",
    "category": "entertainment",
    "title": "Harry Styles breaks his own sales record as new album hits number one / ハリー・スタイルズ、新作アルバムが1位獲得で自身の売上記録を更新",
    "source": "BBC News",
    "timeAgo": "Today",
    "imageUrl": "https://images.unsplash.com/photo-1585829365295-ab7cd400c167?auto=format&fit=crop&q=80&w=1000",
    "readTime": "1 min",
    "vibe": "positive",
    "summary": [
      "人気アーティスト、ハリー・スタイルズの最新アルバムが発売され、大ヒットを記録しました。",
      "この新作は、発売と同時に全英チャートで初登場1位を獲得しました。",
      "アルバムは18万3千枚を売り上げ、ハリー・スタイルズ自身の過去の記録を塗り替えました。"
    ],
    "whyYouShouldCare": "人気アーティストの動向は、音楽業界のトレンドやエンターテイメント文化の盛り上がりを知る上で注目に値します。",
    "isComplex": false
  },
  {
    "id": "14",
    "category": "entertainment",
    "title": "Pink Floyd guitar sold for record-breaking $14.6m",
    "source": "BBC News",
    "timeAgo": "Today",
    "imageUrl": "https://images.unsplash.com/photo-1585829365295-ab7cd400c167?auto=format&fit=crop&q=80&w=1000",
    "readTime": "1 min",
    "vibe": "positive",
    "summary": [
      "ピンク・フロイドのギタリスト、デヴィッド・ギルモアが使用したギターが、史上最高額の1460万ドル（約20億円）で落札されました。",
      "このギターは、バンドの代表作であるアルバム『狂気（Dark Side of the Moon）』などの制作で使われました。",
      "音楽史に残る伝説的な楽器が、いかに高額な価値を持つかを示す記録的な出来事です。"
    ],
    "whyYouShouldCare": "音楽史に残る伝説的な楽器の価値が、いかに高騰しているかを示す事例として、音楽ファンやコレクターにとって興味深いニュースです。",
    "isComplex": false
  },
  {
    "id": "15",
    "category": "entertainment",
    "title": "From Mr Nobody to Oscar nominee: How one man took on Putin",
    "source": "BBC News",
    "timeAgo": "Today",
    "imageUrl": "https://images.unsplash.com/photo-1585829365295-ab7cd400c167?auto=format&fit=crop&q=80&w=1000",
    "readTime": "1 min",
    "vibe": "positive",
    "summary": [
      "パベル・タランキン監督の映画「Mr Nobody Against Putin」が、世界的な注目を集めています。",
      "この作品は既に英国アカデミー賞（BAFTA）を受賞し、その実力が高く評価されています。",
      "現在、映画界最高峰のアカデミー賞（オスカー）の候補作品として、受賞が期待されています。"
    ],
    "whyYouShouldCare": "一人の個人の挑戦が世界的な評価を得るサクセスストーリーは、私たちに勇気と感動を与え、国際的な視点からエンターテイメントの力を再認識させてくれます。",
    "isComplex": false
  },
  {
    "id": "16",
    "category": "it-learning",
    "title": "The 5-File Portfolio That Gets You Hired (No Fancy Design Needed)",
    "source": "DEV Community",
    "timeAgo": "Today",
    "imageUrl": "https://images.unsplash.com/photo-1585829365295-ab7cd400c167?auto=format&fit=crop&q=80&w=1000",
    "readTime": "2 min",
    "vibe": "positive",
    "summary": [
      "従来の美しいウェブサイト型ポートフォリオは採用に繋がりにくく、採用担当者は30秒もかけずに評価している。",
      "採用担当者が重視する5つの要素を、GitHub上の5つのシンプルなMarkdownファイル（README, PROJECTS, BLOG, CONTRIBUTIONS, NOW）で効果的に示す方法を提案。",
      "このアプローチは、自己認識、実績、思考力、協調性、継続的な学習意欲を明確に伝え、他の候補者と差別化し採用の可能性を高める。"
    ],
    "whyYouShouldCare": "就職・転職活動中のITエンジニアやクリエイターが、効果的なポートフォリオ作成を通じて採用のチャンスを高めるための具体的なヒントが得られます。",
    "isComplex": true,
    "eli5Summary": [
      "会社に入りたい時、自分の作ったものを見せる「作品集」が必要だよ。",
      "この作品集は、ピカピカのウェブサイトじゃなくて、簡単なメモ帳みたいなファイル5つで十分なんだ。",
      "大切なのは、何を作ったか、何を考えているか、今何をしているかを正直に書くこと。そうすれば、大人たちは君の頑張りを見てくれるよ！"
    ]
  },
  {
    "id": "17",
    "category": "it-learning",
    "title": "Building a Microservices Ecosystem: Stock Brokerage Simulator (My Broker B3)",
    "source": "DEV Community",
    "timeAgo": "Today",
    "imageUrl": "https://images.unsplash.com/photo-1585829365295-ab7cd400c167?auto=format&fit=crop&q=80&w=1000",
    "readTime": "2 min",
    "vibe": "info",
    "summary": [
      "個人プロジェクト「My Broker B3」として、高度なソフトウェアエンジニアリング技術を駆使した証券取引シミュレーターの開発が開始されました。",
      "マイクロサービスアーキテクチャを採用し、Java/Python、Kafka/RabbitMQ、多様なデータベース（MySQL, MongoDB, Redis）を組み合わせたハイブリッドなシステム設計が特徴です。",
      "データ一貫性、低遅延、非同期通信、マッチングエンジンといった、実際の証券取引システムが直面する複雑な課題解決を目指しています。"
    ],
    "whyYouShouldCare": "このプロジェクトは、現代のデジタルサービスを支える複雑なシステム構築技術の一端を示しており、IT業界で働く人々や、将来IT分野を目指す学生にとって、実践的な知識と技術トレンドを理解する上で役立ちます。",
    "isComplex": true,
    "eli5Summary": [
      "「My Broker B3」は、おもちゃの証券会社を作るプロジェクトだよ。",
      "たくさんの小さなプログラムを組み合わせて、本物の証券会社みたいに株の売買をシミュレーションするんだ。",
      "お金や株の情報を間違えないように、素早くやり取りできるように、色々な工夫がされているんだよ。"
    ]
  },
  {
    "id": "18",
    "category": "it-learning",
    "title": "The Dark Side of 'Vibe Coding' That Nobody Talks About",
    "source": "DEV Community",
    "timeAgo": "Today",
    "imageUrl": "https://images.unsplash.com/photo-1585829365295-ab7cd400c167?auto=format&fit=crop&q=80&w=1000",
    "readTime": "2 min",
    "vibe": "alert",
    "summary": [
      "AIに指示するだけでコードを生成し、内容を深く理解せずに利用する「Vibe Coding」が、技術業界で流行しています。",
      "しかし、デバッグの困難さ、セキュリティ脆弱性、技術的負債の蓄積、個人のキャリア成長の停滞など、多くの危険性が指摘されています。",
      "AIはあくまで「副操縦士」として活用し、生成されたコードを理解し、基礎的な知識を習得することが、安全かつ効果的な利用には不可欠です。"
    ],
    "whyYouShouldCare": "AIによる自動化はプログラミングに限らず多くの仕事に影響を与えるため、その利便性の裏に潜むリスクを理解し、賢く技術を活用する視点を持つことは、現代社会を生きる上で不可欠です。",
    "isComplex": true,
    "eli5Summary": [
      "AIに「こんなアプリを作って」とお願いすると、AIが自動でプログラムを作ってくれるのが「Vibe Coding」だよ。",
      "でも、AIが作ったプログラムの中身を全然知らないと、もし動かなくなったり、悪い人が悪用できる穴があったりしても、直せないから大変なんだ。",
      "だから、AIは便利な道具だけど、ちゃんと中身をチェックして、自分で直せるくらいに勉強することが大切なんだね。"
    ]
  }
]